{
  "productCode": "personal-loan",
  "provider": "kreditbee",
  "tenant": "turtlemint",
  "broker": "turtlemint",
  "skipSequence": true,
  "isLSMNeeded": true,
  "leadData": [
      {
          "stage": "lead-created",
          "status": "lead-created",
          "subStatus": [],
          "action": "PERSONAL_LOAN_ANY",
          "event": "PERSONAL_LOAN_ANY_ANY",
          "isNextStatusAcceptable": true,
          "isEndOfJourneyStatus": false,
          "sequence": 1,
          "leadDisplay": {
              "title": "$leadOrder.leadName",
              "description": "OTP required for CIBIL verification",
              "productChip": {
                  "text": "personal-loan",
                  "icon": "https://app.turtlemint.com/api/files/v1/view/2e8fdfac-c439-451a-91bc-42eb03340dba?broker=turtlemint"
              },
              "sourceChip": {
                  "text": "Online"
              },
              "statusChip": {
                  "text": "Unverified Lead",
                  "color": "YELLOW"
              },
              "detailsTitle": "$leadOrder.leadName",
              "detailsDescription": "OTP required for CIBIL verification",
              "isCallCtaEnabled": false,
              "ctaText": "Complete Application"
          }
      },
      {
          "stage": "general",
          "status": "any",
          "subStatus": [],
          "action": "PERSONAL_LOAN_GENERAL",
          "event": "PERSONAL_LOAN_GENERAL_ANY",
          "isNextStatusAcceptable": true,
          "isEndOfJourneyStatus": false,
          "sequence": 2,
          "leadDisplay": {
              "title": "$leadOrder.leadName",
              "description": "Ask customer to fill the application form",
              "productChip": {
                  "text": "personal-loan",
                  "icon": "https://app.turtlemint.com/api/files/v1/view/2e8fdfac-c439-451a-91bc-42eb03340dba?broker=turtlemint"
              },
              "sourceChip": {
                  "text": "Online"
              },
              "statusChip": {
                  "text": "Verified Lead",
                  "color": "YELLOW"
              },
              "detailsTitle": "$leadOrder.leadName",
              "detailsDescription": "Ask customer to fill the application form",
              "isCallCtaEnabled": false,
              "ctaText": "Complete Application"
          }
      },
      {
          "stage": "eligible",
          "status": "any",
          "subStatus": [],
          "action": "PERSONAL_LOAN_ELIGIBLE",
          "event": "PERSONAL_LOAN_ELIGIBLE_ANY",
          "isNextStatusAcceptable": true,
          "isEndOfJourneyStatus": false,
          "sequence": 3,
          "leadDisplay": {
              "title": "$leadOrder.leadName",
              "description": "Complete Application",
              "productChip": {
                  "text": "personal-loan",
                  "icon": "https://app.turtlemint.com/api/files/v1/view/2e8fdfac-c439-451a-91bc-42eb03340dba?broker=turtlemint"
              },
              "sourceChip": {
                  "text": "Online"
              },
              "statusChip": {
                  "text": "In Progress",
                  "color": "YELLOW"
              },
              "detailsTitle": "$leadOrder.leadName",
              "detailsDescription": "Complete Application",
              "isCallCtaEnabled": false,
              "ctaText": "Customer KYC Pending"
          }
      },
      {
          "stage": "confirmed without principal due",
          "status": "any",
          "subStatus": [],
          "action": "PERSONAL_LOAN_CONFIRMED_WITHOUT_PRINCIPALDUE",
          "event": "PERSONAL_LOAN_CONFIRMED_WITHOUT_PRINCIPALDUE_ANY",
          "isNextStatusAcceptable": true,
          "isEndOfJourneyStatus": false,
          "sequence": 4,
          "leadDisplay": {
              "title": "$leadOrder.leadName",
              "description": "Loan offer available",
              "productChip": {
                  "text": "personal-loan",
                  "icon": "https://app.turtlemint.com/api/files/v1/view/2e8fdfac-c439-451a-91bc-42eb03340dba?broker=turtlemint"
              },
              "sourceChip": {
                  "text": "Online"
              },
              "statusChip": {
                  "text": "In Progress",
                  "color": "YELLOW"
              },
              "detailsTitle": "$leadOrder.leadName",
              "detailsDescription": "Loan offer available",
              "isCallCtaEnabled": false,
              "ctaText": "Complete Application"
          }
      },
      {
          "stage": "confirmed with principal due",
          "status": "any",
          "subStatus": [],
          "action": "PERSONAL_LOAN_CONFIRMED_WITH_PRINCIPALDUE",
          "event": "PERSONAL_LOAN_CONFIRMED_WITH_PRINCIPALDUE_ANY",
          "isNextStatusAcceptable": true,
          "isEndOfJourneyStatus": false,
          "sequence": 5,
          "leadDisplay": {
              "title": "$leadOrder.leadName",
              "description": "Loan disbursed",
              "productChip": {
                  "text": "personal-loan",
                  "icon": "https://app.turtlemint.com/api/files/v1/view/2e8fdfac-c439-451a-91bc-42eb03340dba?broker=turtlemint"
              },
              "sourceChip": {
                  "text": "Online"
              },
              "statusChip": {
                  "text": "Completed",
                  "color": "GREEN"
              },
              "detailsTitle": "$leadOrder.leadName",
              "detailsDescription": "Loan disbursed",
              "isCallCtaEnabled": false
          }
      },
      {
          "stage": "rejected",
          "status": "any",
          "subStatus": [],
          "action": "PERSONAL_LOAN_REJECTED",
          "event": "PERSONAL_LOAN_REJECTED_ANY",
          "isNextStatusAcceptable": true,
          "isEndOfJourneyStatus": false,
          "sequence": 6,
          "leadDisplay": {
              "title": "$leadOrder.leadName",
              "description": "Scorecard decline due to credit history",
              "productChip": {
                  "text": "personal-loan",
                  "icon": "https://app.turtlemint.com/api/files/v1/view/2e8fdfac-c439-451a-91bc-42eb03340dba?broker=turtlemint"
              },
              "sourceChip": {
                  "text": "Online"
              },
              "statusChip": {
                  "text": "Rejected",
                  "color": "RED"
              },
              "detailsTitle": "$leadOrder.leadName",
              "detailsDescription": "Scorecard decline due to credit history",
              "isCallCtaEnabled": false
          }
      }
  ],
  "updatedBy": "ankit.singh"
}